synthesized_datasets/__init__.py
synthesized_datasets/_datasets.py
synthesized_datasets/_dtypes.py
synthesized_datasets/datasets.yaml
synthesized_datasets/version.py
synthesized_datasets-1.7.dist-info/LICENSE.md
synthesized_datasets-1.7.dist-info/METADATA
synthesized_datasets-1.7.dist-info/WHEEL
synthesized_datasets-1.7.dist-info/top_level.txt
synthesized_datasets-1.7.dist-info/RECORD
