Metadata-Version: 2.1
Name: synthesized-datasets
Version: 1.7
Summary: Publically available datasets for benchmarking and evaluation.
Author-email: "Synthesized Ltd." <sdk-team@synthesized.io>
License: BSD 3-Clause License
Project-URL: homepage, https://synthesized.io
Project-URL: documentation, https://docs.synthesized.io/
Project-URL: repository, https://github.com/synthesized-io/datasets
Keywords: datasets,data,evaluation
Platform: MacOS
Platform: Windows
Platform: Linux
Classifier: Development Status :: 5 - Production/Stable
Classifier: License :: OSI Approved :: BSD License
Classifier: Intended Audience :: Developers
Classifier: Intended Audience :: Science/Research
Classifier: Operating System :: MacOS
Classifier: Operating System :: Microsoft :: Windows
Classifier: Operating System :: POSIX
Classifier: Operating System :: Unix
Classifier: Programming Language :: Python :: 3
Classifier: Programming Language :: Python :: 3 :: Only
Classifier: Programming Language :: Python :: 3.7
Classifier: Programming Language :: Python :: 3.8
Classifier: Programming Language :: Python :: 3.9
Classifier: Topic :: Scientific/Engineering
Requires-Python: >=3.7
License-File: LICENSE.md
Requires-Dist: pandas >=1.2
Requires-Dist: pyspark >=0.7.0
Requires-Dist: fastparquet
Provides-Extra: dev
Requires-Dist: pre-commit ; extra == 'dev'
Requires-Dist: black ; extra == 'dev'
Requires-Dist: mypy ; extra == 'dev'
Requires-Dist: pylint ; extra == 'dev'
